sphinx2rst/__init__.py
sphinx2rst/__main__.py
sphinx2rst-1.1.0.dist-info/DESCRIPTION.rst
sphinx2rst-1.1.0.dist-info/METADATA
sphinx2rst-1.1.0.dist-info/RECORD
sphinx2rst-1.1.0.dist-info/WHEEL
sphinx2rst-1.1.0.dist-info/entry_points.txt
sphinx2rst-1.1.0.dist-info/metadata.json
sphinx2rst-1.1.0.dist-info/top_level.txt
